{
    "version": "2.71",
    "description": "A music transcription helper that analyzes audio files and displays the sound like a piano roll.",
    "homepage": "http://ackiesound.ifdef.jp/download.html#wt",
    "license": "Freeware",
    "notes": [
        "This is not a portable software.",
        "Setting files are saved in \"%appdata%\\ackiesound\\wavetone\"."
    ],
    "url": "http://ackiesound.ifdef.jp/data/wavetone271.zip",
    "hash": "e280c9735e31eb2bc0ed679a42424430ba27809f122da9e284579983c212d747",
    "extract_dir": "wavetone271",
    "checkver": "WaveTone ver.(\\d\\.\\d+)",
    "shortcuts": [
        [
            "wavetone.exe",
            "WaveTone"
        ]
    ],
    "autoupdate": {
        "url": "http://ackiesound.ifdef.jp/data/wavetone$cleanVersion.zip",
        "extract_dir": "wavetone$cleanVersion"
    }
}
